LICENSE
README.md
setup.py
SpacePuma.egg-info/PKG-INFO
SpacePuma.egg-info/SOURCES.txt
SpacePuma.egg-info/dependency_links.txt
SpacePuma.egg-info/requires.txt
SpacePuma.egg-info/top_level.txt
spacepuma/__init__.py
spacepuma/base.py
spacepuma/baseline.py
spacepuma/display_tools.py
spacepuma/export.py
spacepuma/fit.py
spacepuma/fit_gaussian.py
spacepuma/fit_methods.py
spacepuma/gaussian_fit.py
spacepuma/int_peaks.py
spacepuma/labels.py
spacepuma/main_menu.py
spacepuma/spacepuma.py
spacepuma/template_fit.py