Metadata-Version: 2.1
Name: SpacePuma
Version: 0.2
Summary: Interact with your data.
Home-page: https://github.com/alexdelfranco/SpacePuma
Author: Alex DelFranco
Author-email: adelfranco24@amherst.edu
License: MIT
Classifier: Programming Language :: Python :: 3.9
Classifier: License :: OSI Approved :: MIT License
Classifier: Operating System :: OS Independent
License-File: LICENSE
